voicefixer/__init__.py
voicefixer/__main__.py
voicefixer/base.py
voicefixer/cli.py
voicefixer/legacycli.py
voicefixer/restorer/__init__.py
voicefixer/restorer/model.py
voicefixer/restorer/model_kqq_bn.py
voicefixer/restorer/modules.py
voicefixer/tools/__init__.py
voicefixer/tools/base.py
voicefixer/tools/io.py
voicefixer/tools/mel_scale.py
voicefixer/tools/pytorch_util.py
voicefixer/tools/random_.py
voicefixer/tools/wav.py
voicefixer/tools/modules/__init__.py
voicefixer/tools/modules/fDomainHelper.py
voicefixer/tools/modules/pqmf.py
voicefixer/vocoder/__init__.py
voicefixer/vocoder/base.py
voicefixer/vocoder/config.py
voicefixer/vocoder/model/__init__.py
voicefixer/vocoder/model/generator.py
voicefixer/vocoder/model/modules.py
voicefixer/vocoder/model/pqmf.py
voicefixer/vocoder/model/res_msd.py
voicefixer/vocoder/model/util.py
voicefixer2-3.0.0.dist-info/LICENSE
voicefixer2-3.0.0.dist-info/METADATA
voicefixer2-3.0.0.dist-info/WHEEL
voicefixer2-3.0.0.dist-info/entry_points.txt
voicefixer2-3.0.0.dist-info/top_level.txt
voicefixer2-3.0.0.dist-info/RECORD
