Metadata-Version: 2.1
Name: voicefixer2
Version: 3.0.0
Summary: General speech restoration toolkit.
Home-page: https://github.com/voicefixer/voicefixer
Author: mrfakename
Author-email: me@mrfake.name
License: VoiceFixer (BSD-3 + logo restriction)
Classifier: Programming Language :: Python
Classifier: Programming Language :: Python :: 3
Classifier: Programming Language :: Python :: 3.9
Requires-Python: >=3.7.0
License-File: LICENSE
Requires-Dist: matplotlib
Requires-Dist: cached-path
Requires-Dist: torch >=1.7.0
Requires-Dist: progressbar
Requires-Dist: torchlibrosa
Requires-Dist: GitPython
Requires-Dist: streamlit
Requires-Dist: pyyaml
Requires-Dist: pydub
Requires-Dist: scipy
Requires-Dist: soundfile
Requires-Dist: librosa
Requires-Dist: click
Provides-Extra: docs
Requires-Dist: sphinxawesome-theme ; extra == 'docs'
Requires-Dist: myst-parser ; extra == 'docs'
Requires-Dist: sphinx-notfound-page ; extra == 'docs'
Requires-Dist: sphinx-design ; extra == 'docs'
